px/__init__.py
px/px_pb2.py
px/px_pb2_grpc.py
px_client/__init__.py
px_client/client.py
px_server/__init__.py
px_server/helper.py
px_server/server.py
ckpx-0.0.9.dist-info/METADATA
ckpx-0.0.9.dist-info/WHEEL
ckpx-0.0.9.dist-info/top_level.txt
ckpx-0.0.9.dist-info/RECORD
